acadyne/__init__.py
acadyne/tensores/__init__.py
acadyne/tensores/dynamic_tensor.py
acadyne/tensores/lorentz_tensor.py
acadyne/tensores/set_tensor.py
acadyne/test/__init__.py
acadyne-0.3.2.dist-info/LICENSE
acadyne-0.3.2.dist-info/METADATA
acadyne-0.3.2.dist-info/WHEEL
acadyne-0.3.2.dist-info/top_level.txt
acadyne-0.3.2.dist-info/RECORD
