Metadata-Version: 2.1
Name: acadyne
Version: 0.3.2
Summary: Una biblioteca biónica para la manipulación de tensores numéricos y simbólicos, facilitando cálculos avanzados en computación científica.
Home-page: https://github.com/acadyne/acadyne
Author: Jose Fabian Soltero Escobar
Author-email: Jose Fabian Soltero Escobar <acadyne@gmail.com>
License: MIT
Project-URL: homepage, https://github.com/acadyne/acadyne
Project-URL: repository, https://github.com/acadyne/acadyne
Project-URL: documentation, https://github.com/acadyne/acadyne/wiki
Keywords: tensor,computation,symbolic,mathematics,simulation,bionic
Classifier: Development Status :: 4 - Beta
Classifier: Intended Audience :: Developers
Classifier: Intended Audience :: Science/Research
Classifier: License :: OSI Approved :: MIT License
Classifier: Programming Language :: Python :: 3
Classifier: Programming Language :: Python :: 3.7
Classifier: Programming Language :: Python :: 3.8
Classifier: Programming Language :: Python :: 3.9
Classifier: Programming Language :: Python :: 3.10
Classifier: Operating System :: OS Independent
Classifier: Topic :: Scientific/Engineering :: Mathematics
Requires-Python: >=3.7
License-File: LICENSE
Requires-Dist: numpy>=1.21
Requires-Dist: sympy>=1.8
Requires-Dist: scipy>=1.5
Requires-Dist: pandas>=1.0
Requires-Dist: matplotlib>=3.0
Provides-Extra: testing
Requires-Dist: pytest; extra == "testing"
Requires-Dist: pytest-cov; extra == "testing"
Requires-Dist: flake8; extra == "testing"
